ppyimgur-0.6.0.post1.dist-info/METADATA
ppyimgur-0.6.0.post1.dist-info/RECORD
ppyimgur-0.6.0.post1.dist-info/WHEEL
ppyimgur-0.6.0.post1.dist-info/top_level.txt
pyimgur/__init__.py
pyimgur/request.py
