Metadata-Version: 2.1
Name: ppyimgur
Version: 0.6.0.post1
Summary: The easy way of using Imgur.
Home-page: https://github.com/Damgaard/PyImgur
Author: Andreas Damgaard Pedersen
Author-email: andreas.damgaard.pedersen@gmail.com
License: GPLv3
Keywords: imgur api wrapper PyImgur
Platform: UNKNOWN
Classifier: Development Status :: 4 - Beta
Classifier: Environment :: Console
Classifier: Intended Audience :: Developers
Classifier: License :: OSI Approved :: GNU General Public License (GPL)
Classifier: Natural Language :: English
Classifier: Operating System :: OS Independent
Classifier: Programming Language :: Python :: 2.7
Classifier: Topic :: Utilities
Requires-Dist: requests
